pyFPLdata/__init__.py
pyFPLdata/script.py
pyFPLdata-1.0.0.dist-info/LICENCE
pyFPLdata-1.0.0.dist-info/METADATA
pyFPLdata-1.0.0.dist-info/WHEEL
pyFPLdata-1.0.0.dist-info/top_level.txt
pyFPLdata-1.0.0.dist-info/RECORD
