Metadata-Version: 2.1
Name: pyFPLdata
Version: 1.0.0
Summary: Read in Fantasy Premier League Data
Home-page: https://github.com/andrewl776/FPLdata_py
Author: Andrew Little
Author-email: andrewlittlebristol@gmail.com
Project-URL: Bug Tracker, https://github.com/andrewl776/FPLdata_py/issues
Classifier: Programming Language :: Python :: 3
Classifier: License :: OSI Approved :: MIT License
Classifier: Operating System :: OS Independent
Requires-Python: >=3.6
License-File: LICENCE
